claude_git/__init__.py
claude_git/post_tool_use.py
claude_git/session_start.py
claude_git/shared_sagas.py
claude_git/undo.py
claude_git-0.1.2.dist-info/METADATA
claude_git-0.1.2.dist-info/WHEEL
claude_git-0.1.2.dist-info/entry_points.txt
claude_git-0.1.2.dist-info/top_level.txt
claude_git-0.1.2.dist-info/RECORD
