Metadata-Version: 2.4
Name: claude-git
Version: 0.1.2
Summary: Create a git worktree that tracks claude-code changes without polluting the main repo's git history
Requires-Python: >=3.13
Requires-Dist: claude-saga>=0.1.2
Provides-Extra: dev
Requires-Dist: ruff>=0.7.0; extra == "dev"
Requires-Dist: pytest>=8.0.0; extra == "dev"
